LICENSE.txt
setup.py
T1TV/__init__.py
T1TV.egg-info/PKG-INFO
T1TV.egg-info/SOURCES.txt
T1TV.egg-info/dependency_links.txt
T1TV.egg-info/top_level.txt