Metadata-Version: 2.1
Name: T1TV
Version: 0.1
Summary: With this library, you can search and download from akwam.to, and you can also create IPTV and search any m3u_plus
Author: VIRUS
Classifier: Programming Language :: Python :: 3
Classifier: Operating System :: OS Independent
Classifier: License :: OSI Approved :: MIT License
License-File: LICENSE.txt
